{
  "trainingPhrases": [ {
    "parts": [ {
      "text": "Where does the Consumer Services business operate geographically?",
      "auto": true
    } ],
    "repeatCount": 1,
    "languageCode": "en"
  }, {
    "parts": [ {
      "text": "Is senior management expecting to change guidance in the ",
      "auto": true
    }, {
      "text": "second half",
      "parameterId": "date-time",
      "auto": true
    }, {
      "text": "?",
      "auto": true
    } ],
    "repeatCount": 1,
    "languageCode": "en"
  }, {
    "parts": [ {
      "text": "Will economic headwinds negatively impact guidance for the second half of the year?"
    } ],
    "repeatCount": 1,
    "languageCode": "en"
  }, {
    "parts": [ {
      "text": "What will the ",
      "auto": true
    }, {
      "text": "Experian",
      "parameterId": "competitors",
      "auto": true
    }, {
      "text": "'s LATM consumer business revenue be for the full year?",
      "auto": true
    } ],
    "repeatCount": 1,
    "languageCode": "en"
  }, {
    "parts": [ {
      "text": "What is the value of the ",
      "auto": true
    }, {
      "text": "Experian",
      "parameterId": "competitors",
      "auto": true
    }, {
      "text": "'s initiated share buyback program and when is it expected to be completed?",
      "auto": true
    } ],
    "repeatCount": 1,
    "languageCode": "en"
  }, {
    "parts": [ {
      "text": "Was the ",
      "auto": true
    }, {
      "text": "Experian",
      "parameterId": "competitors",
      "auto": true
    }, {
      "text": "'s EBIT margin for the ",
      "auto": true
    }, {
      "text": "second quarter",
      "parameterId": "date-period",
      "auto": true
    }, {
      "text": " in line with guidance?",
      "auto": true
    } ],
    "repeatCount": 1,
    "languageCode": "en"
  }, {
    "parts": [ {
      "text": "How did mortgage ",
      "auto": true
    }, {
      "text": "Experian",
      "parameterId": "competitors",
      "auto": true
    }, {
      "text": "'s revenue perform in the ",
      "auto": true
    }, {
      "text": "second quarter",
      "parameterId": "date-period",
      "auto": true
    }, {
      "text": "?",
      "auto": true
    } ],
    "repeatCount": 1,
    "languageCode": "en"
  }, {
    "parts": [ {
      "text": "Is there any progress with Income Verifications for "
    }, {
      "text": "Experian",
      "parameterId": "competitors",
      "auto": true
    }, {
      "text": " outside of the "
    }, {
      "text": "US",
      "parameterId": "geo-country"
    }, {
      "text": "?"
    } ],
    "repeatCount": 1,
    "languageCode": "en"
  }, {
    "parts": [ {
      "text": "How many income and employment records are available now in ",
      "auto": true
    }, {
      "text": "Experian",
      "parameterId": "competitors",
      "auto": true
    }, {
      "text": "?",
      "auto": true
    } ],
    "repeatCount": 1,
    "languageCode": "en"
  }, {
    "parts": [ {
      "text": "How much growth is expected for Income and Employment Verifications for "
    }, {
      "text": "Experian",
      "parameterId": "competitors",
      "auto": true
    }, {
      "text": " in "
    }, {
      "text": "2024",
      "parameterId": "fiscal_year"
    }, {
      "text": "?"
    } ],
    "repeatCount": 1,
    "languageCode": "en"
  }, {
    "parts": [ {
      "text": "What is the estimated "
    }, {
      "text": "Experian",
      "parameterId": "competitors",
      "auto": true
    }, {
      "text": "'s revenue in fiscal year "
    }, {
      "text": "2024",
      "parameterId": "fiscal_year"
    }, {
      "text": " for Income and Employment Verifications segment?"
    } ],
    "repeatCount": 1,
    "languageCode": "en"
  } ]
}
